kadmin_local
