Metadata-Version: 1.2
Name: kadmin-local
Version: 0.0.2
Summary: Python module for kerberos admin (kadm5) via root local interface
Home-page: https://github.com/nightfly19/python-kadmin
Author: Russell Jancewicz, Sage Imel
Author-email: sageimel@gmail.com
License: MIT
Download-URL: https://github.com/nightfly19/python-kadmin/tarball/v0.0.2
Platform: UNKNOWN
Classifier: Development Status :: 4 - Beta
Classifier: Environment :: Console
Classifier: Intended Audience :: System Administrators
Classifier: Intended Audience :: Developers
Classifier: Operating System :: POSIX
Classifier: Programming Language :: C
Classifier: Programming Language :: Python
Classifier: Programming Language :: YACC
Classifier: License :: OSI Approved :: MIT License
Classifier: Topic :: Software Development :: Libraries :: Python Modules
Classifier: Topic :: System :: Systems Administration :: Authentication/Directory
Requires-Python: >=3.5
